{
  "temas": {
    "tema_01": {
      "tests": [
        {
          "nombre": "Test 1 — Derechos Humanos",
          "archivo": "sargento/conocimientos/tema_01/tema_01_test_01.json",
          "preguntas": 20
        },
        {
          "nombre": "Test 2 — Derechos Humanos",
          "archivo": "sargento/conocimientos/tema_01/tema_01_test_02.json",
          "preguntas": 20
        },
        {
          "nombre": "Test 3 — Derechos Humanos",
          "archivo": "sargento/conocimientos/tema_01/tema_01_test_03.json",
          "preguntas": 20
        },
        {
          "nombre": "Test 4 — Derechos Humanos",
          "archivo": "sargento/conocimientos/tema_01/tema_01_test_04.json",
          "preguntas": 20
        },
        {
          "nombre": "Test 5 — Derechos Humanos",
          "archivo": "sargento/conocimientos/tema_01/tema_01_test_05.json",
          "preguntas": 20
        },
        {
          "nombre": "Test 6 — Derechos Humanos",
          "archivo": "sargento/conocimientos/tema_01/tema_01_test_06.json",
          "preguntas": 20
        },
        {
          "nombre": "Test 7 — Derechos Humanos",
          "archivo": "sargento/conocimientos/tema_01/tema_01_test_07.json",
          "preguntas": 20
        },
        {
          "nombre": "Test 8 — Derechos Humanos",
          "archivo": "sargento/conocimientos/tema_01/tema_01_test_08.json",
          "preguntas": 20
        },
        {
          "nombre": "Test 9 — Derechos Humanos",
          "archivo": "sargento/conocimientos/tema_01/tema_01_test_09.json",
          "preguntas": 20
        },
        {
          "nombre": "Test 10 — Derechos Humanos",
          "archivo": "sargento/conocimientos/tema_01/tema_01_test_10.json",
          "preguntas": 20
        },
        {
          "nombre": "Test 11 — Derechos Humanos",
          "archivo": "sargento/conocimientos/tema_01/tema_01_test_11.json",
          "preguntas": 20
        },
        {
          "nombre": "Test 12 — Derechos Humanos",
          "archivo": "sargento/conocimientos/tema_01/tema_01_test_12.json",
          "preguntas": 20
        },
        {
          "nombre": "Test 13 — Derechos Humanos",
          "archivo": "sargento/conocimientos/tema_01/tema_01_test_13.json",
          "preguntas": 20
        },
        {
          "nombre": "Test 14 — Derechos Humanos",
          "archivo": "sargento/conocimientos/tema_01/tema_01_test_14.json",
          "preguntas": 20
        },
        {
          "nombre": "Test 15 — Derechos Humanos",
          "archivo": "sargento/conocimientos/tema_01/tema_01_test_15.json",
          "preguntas": 20
        },
        {
          "nombre": "Test 16 — Derechos Humanos",
          "archivo": "sargento/conocimientos/tema_01/tema_01_test_16.json",
          "preguntas": 20
        },
        {
          "nombre": "Test 17 — Derechos Humanos",
          "archivo": "sargento/conocimientos/tema_01/tema_01_test_17.json",
          "preguntas": 20
        },
        {
          "nombre": "Test 18 — Derechos Humanos",
          "archivo": "sargento/conocimientos/tema_01/tema_01_test_18.json",
          "preguntas": 20
        },
        {
          "nombre": "Test 19 — Derechos Humanos",
          "archivo": "sargento/conocimientos/tema_01/tema_01_test_19.json",
          "preguntas": 20
        },
        {
          "nombre": "Test 20 — Derechos Humanos",
          "archivo": "sargento/conocimientos/tema_01/tema_01_test_20.json",
          "preguntas": 20
        },
        {
          "nombre": "Test 21 — Tema 1 - Derechos Humanos",
          "archivo": "sargento/conocimientos/tema_01/tema_01_test_21.json",
          "preguntas": 20
        },
        {
          "nombre": "Test 22 — Tema 1 - Derechos Humanos",
          "archivo": "sargento/conocimientos/tema_01/tema_01_test_22.json",
          "preguntas": 20
        }
      ],
      "total_preguntas": 440
    },
    "tema_02": {
      "tests": [],
      "total_preguntas": 0
    },
    "tema_03": {
      "tests": [],
      "total_preguntas": 0
    },
    "tema_04": {
      "tests": [],
      "total_preguntas": 0
    },
    "tema_05": {
      "tests": [],
      "total_preguntas": 0
    },
    "tema_06": {
      "tests": [
        {
          "nombre": "Test 1 — Poder Judicial",
          "archivo": "sargento/conocimientos/tema_06/tema_06_test_01.json",
          "preguntas": 20
        },
        {
          "nombre": "Test 2 — Poder Judicial",
          "archivo": "sargento/conocimientos/tema_06/tema_06_test_02.json",
          "preguntas": 20
        },
        {
          "nombre": "Test 3 — Tema 6 - Poder Judicial",
          "archivo": "sargento/conocimientos/tema_06/tema_06_test_03.json",
          "preguntas": 20
        },
        {
          "nombre": "Test 4 — Tema 6 - Poder Judicial",
          "archivo": "sargento/conocimientos/tema_06/tema_06_test_04.json",
          "preguntas": 20
        },
        {
          "nombre": "Test 5 — Tema 6 - Poder Judicial",
          "archivo": "sargento/conocimientos/tema_06/tema_06_test_05.json",
          "preguntas": 20
        },
        {
          "nombre": "Test 6 — Tema 6 - Poder Judicial",
          "archivo": "sargento/conocimientos/tema_06/tema_06_test_06.json",
          "preguntas": 20
        },
        {
          "nombre": "Test 7 — Tema 6 - Poder Judicial",
          "archivo": "sargento/conocimientos/tema_06/tema_06_test_07.json",
          "preguntas": 20
        },
        {
          "nombre": "Test 8 — Tema 6 - Poder Judicial",
          "archivo": "sargento/conocimientos/tema_06/tema_06_test_08.json",
          "preguntas": 20
        },
        {
          "nombre": "Test 9 — Tema 6 - Poder Judicial",
          "archivo": "sargento/conocimientos/tema_06/tema_06_test_09.json",
          "preguntas": 20
        },
        {
          "nombre": "Test 10 — Tema 6 - Poder Judicial",
          "archivo": "sargento/conocimientos/tema_06/tema_06_test_10.json",
          "preguntas": 20
        },
        {
          "nombre": "Test 11 — Tema 6 - Poder Judicial",
          "archivo": "sargento/conocimientos/tema_06/tema_06_test_11.json",
          "preguntas": 20
        },
        {
          "nombre": "Test 12 — Tema 6 - Poder Judicial",
          "archivo": "sargento/conocimientos/tema_06/tema_06_test_12.json",
          "preguntas": 20
        },
        {
          "nombre": "Test 13 — Tema 6 - Poder Judicial",
          "archivo": "sargento/conocimientos/tema_06/tema_06_test_13.json",
          "preguntas": 20
        },
        {
          "nombre": "Test 14 — Tema 6 - Poder Judicial",
          "archivo": "sargento/conocimientos/tema_06/tema_06_test_14.json",
          "preguntas": 20
        },
        {
          "nombre": "Test 15 — Tema 6 - Poder Judicial",
          "archivo": "sargento/conocimientos/tema_06/tema_06_test_15.json",
          "preguntas": 20
        },
        {
          "nombre": "Test 16 — Tema 6 - Poder Judicial",
          "archivo": "sargento/conocimientos/tema_06/tema_06_test_16.json",
          "preguntas": 20
        },
        {
          "nombre": "Test 17 — Tema 6 - Poder Judicial",
          "archivo": "sargento/conocimientos/tema_06/tema_06_test_17.json",
          "preguntas": 20
        },
        {
          "nombre": "Test 18 — Tema 6 - Poder Judicial",
          "archivo": "sargento/conocimientos/tema_06/tema_06_test_18.json",
          "preguntas": 20
        },
        {
          "nombre": "Test 19 — Tema 6 - Poder Judicial",
          "archivo": "sargento/conocimientos/tema_06/tema_06_test_19.json",
          "preguntas": 20
        },
        {
          "nombre": "Test 20 — Tema 6 - Poder Judicial",
          "archivo": "sargento/conocimientos/tema_06/tema_06_test_20.json",
          "preguntas": 20
        },
        {
          "nombre": "Test 21 — Tema 6 - Poder Judicial",
          "archivo": "sargento/conocimientos/tema_06/tema_06_test_21.json",
          "preguntas": 20
        },
        {
          "nombre": "Test 22 — Tema 6 - Poder Judicial",
          "archivo": "sargento/conocimientos/tema_06/tema_06_test_22.json",
          "preguntas": 20
        }
      ],
      "total_preguntas": 440
    },
    "tema_07": {
      "tests": [],
      "total_preguntas": 0
    },
    "tema_08": {
      "tests": [],
      "total_preguntas": 0
    },
    "tema_09": {
      "tests": [],
      "total_preguntas": 0
    },
    "tema_10": {
      "tests": [],
      "total_preguntas": 0
    },
    "tema_11": {
      "tests": [],
      "total_preguntas": 0
    },
    "tema_12": {
      "tests": [],
      "total_preguntas": 0
    },
    "tema_13": {
      "tests": [
        {
          "nombre": "Test 1 — Tema 13 - Normas Complementarias del Derecho Procesal",
          "archivo": "sargento/conocimientos/tema_13/tema_13_sub13.1_test_01.json",
          "preguntas": 20,
          "subtema": "13.1"
        },
        {
          "nombre": "Test 2 — Tema 13 - Normas Complementarias del Derecho Procesal",
          "archivo": "sargento/conocimientos/tema_13/tema_13_sub13.1_test_02.json",
          "preguntas": 20,
          "subtema": "13.1"
        },
        {
          "nombre": "Test 3 — Tema 13 - Normas Complementarias del Derecho Procesal",
          "archivo": "sargento/conocimientos/tema_13/tema_13_sub13.1_test_03.json",
          "preguntas": 20,
          "subtema": "13.1"
        },
        {
          "nombre": "Test 4 — Tema 13 - Normas Complementarias del Derecho Procesal",
          "archivo": "sargento/conocimientos/tema_13/tema_13_sub13.1_test_04.json",
          "preguntas": 20,
          "subtema": "13.1"
        },
        {
          "nombre": "Test 5 — Tema 13 - Normas Complementarias del Derecho Procesal",
          "archivo": "sargento/conocimientos/tema_13/tema_13_sub13.1_test_05.json",
          "preguntas": 20,
          "subtema": "13.1"
        },
        {
          "nombre": "Test 6 — Tema 13 - Normas Complementarias del Derecho Procesal",
          "archivo": "sargento/conocimientos/tema_13/tema_13_sub13.1_test_06.json",
          "preguntas": 20,
          "subtema": "13.1"
        },
        {
          "nombre": "Test 7 — Tema 13 - Normas Complementarias del Derecho Procesal",
          "archivo": "sargento/conocimientos/tema_13/tema_13_sub13.1_test_07.json",
          "preguntas": 20,
          "subtema": "13.1"
        },
        {
          "nombre": "Test 8 — Tema 13 - Normas Complementarias del Derecho Procesal",
          "archivo": "sargento/conocimientos/tema_13/tema_13_sub13.1_test_08.json",
          "preguntas": 20,
          "subtema": "13.1"
        },
        {
          "nombre": "Test 9 — Tema 13 - Normas Complementarias del Derecho Procesal",
          "archivo": "sargento/conocimientos/tema_13/tema_13_sub13.1_test_09.json",
          "preguntas": 20,
          "subtema": "13.1"
        },
        {
          "nombre": "Test 10 — Tema 13 - Normas Complementarias del Derecho Procesal",
          "archivo": "sargento/conocimientos/tema_13/tema_13_sub13.1_test_10.json",
          "preguntas": 20,
          "subtema": "13.1"
        },
        {
          "nombre": "Test 11 — Tema 13 - Normas Complementarias del Derecho Procesal",
          "archivo": "sargento/conocimientos/tema_13/tema_13_sub13.1_test_11.json",
          "preguntas": 20,
          "subtema": "13.1"
        },
        {
          "nombre": "Test 12 — Tema 13 - Normas Complementarias del Derecho Procesal",
          "archivo": "sargento/conocimientos/tema_13/tema_13_sub13.1_test_12.json",
          "preguntas": 20,
          "subtema": "13.1"
        },
        {
          "nombre": "Test 1 — Tema 13 - Normas Complementarias del Derecho Procesal",
          "archivo": "sargento/conocimientos/tema_13/tema_13_sub13.2_test_01.json",
          "preguntas": 20,
          "subtema": "13.2"
        },
        {
          "nombre": "Test 2 — Tema 13 - Normas Complementarias del Derecho Procesal",
          "archivo": "sargento/conocimientos/tema_13/tema_13_sub13.2_test_02.json",
          "preguntas": 20,
          "subtema": "13.2"
        },
        {
          "nombre": "Test 3 — Tema 13 - Normas Complementarias del Derecho Procesal",
          "archivo": "sargento/conocimientos/tema_13/tema_13_sub13.2_test_03.json",
          "preguntas": 20,
          "subtema": "13.2"
        },
        {
          "nombre": "Test 4 — Tema 13 - Normas Complementarias del Derecho Procesal",
          "archivo": "sargento/conocimientos/tema_13/tema_13_sub13.2_test_04.json",
          "preguntas": 20,
          "subtema": "13.2"
        },
        {
          "nombre": "Test 5 — Tema 13 - Normas Complementarias del Derecho Procesal",
          "archivo": "sargento/conocimientos/tema_13/tema_13_sub13.2_test_05.json",
          "preguntas": 20,
          "subtema": "13.2"
        },
        {
          "nombre": "Test 6 — Tema 13 - Normas Complementarias del Derecho Procesal",
          "archivo": "sargento/conocimientos/tema_13/tema_13_sub13.2_test_06.json",
          "preguntas": 20,
          "subtema": "13.2"
        },
        {
          "nombre": "Test 7 — Tema 13 - Normas Complementarias del Derecho Procesal",
          "archivo": "sargento/conocimientos/tema_13/tema_13_sub13.2_test_07.json",
          "preguntas": 20,
          "subtema": "13.2"
        },
        {
          "nombre": "Test 8 — Tema 13 - Normas Complementarias del Derecho Procesal",
          "archivo": "sargento/conocimientos/tema_13/tema_13_sub13.2_test_08.json",
          "preguntas": 20,
          "subtema": "13.2"
        },
        {
          "nombre": "Test 9 — Tema 13 - Normas Complementarias del Derecho Procesal",
          "archivo": "sargento/conocimientos/tema_13/tema_13_sub13.2_test_09.json",
          "preguntas": 20,
          "subtema": "13.2"
        },
        {
          "nombre": "Test 10 — Tema 13 - Normas Complementarias del Derecho Procesal",
          "archivo": "sargento/conocimientos/tema_13/tema_13_sub13.2_test_10.json",
          "preguntas": 20,
          "subtema": "13.2"
        },
        {
          "nombre": "Test 11 — Tema 13 - Normas Complementarias del Derecho Procesal",
          "archivo": "sargento/conocimientos/tema_13/tema_13_sub13.2_test_11.json",
          "preguntas": 20,
          "subtema": "13.2"
        },
        {
          "nombre": "Test 12 — Tema 13 - Normas Complementarias del Derecho Procesal",
          "archivo": "sargento/conocimientos/tema_13/tema_13_sub13.2_test_12.json",
          "preguntas": 20,
          "subtema": "13.2"
        }
      ],
      "total_preguntas": 480
    },
    "tema_14": {
      "tests": [],
      "total_preguntas": 0
    },
    "tema_15": {
      "tests": [],
      "total_preguntas": 0
    },
    "tema_16": {
      "tests": [],
      "total_preguntas": 0
    },
    "tema_17": {
      "tests": [],
      "total_preguntas": 0
    },
    "tema_18": {
      "tests": [
        {
          "nombre": "Test 2 — Tema 18 - Seguridad Privada",
          "archivo": "sargento/conocimientos/tema_18/tema_18_test_02.json",
          "preguntas": 20
        },
        {
          "nombre": "Test 3 — Tema 18 - Seguridad Privada",
          "archivo": "sargento/conocimientos/tema_18/tema_18_test_03.json",
          "preguntas": 20
        }
      ],
      "total_preguntas": 40
    },
    "tema_19": {
      "tests": [],
      "total_preguntas": 0
    },
    "tema_20": {
      "tests": [],
      "total_preguntas": 0
    },
    "tema_21": {
      "tests": [],
      "total_preguntas": 0
    },
    "tema_22": {
      "tests": [
        {
          "nombre": "Test 1 — Tema 22 - Fuerzas y Cuerpos de Seguridad",
          "archivo": "sargento/conocimientos/tema_22/tema_22_sub22.1_test_01.json",
          "preguntas": 20,
          "subtema": "22.1"
        },
        {
          "nombre": "Test 2 — Tema 22 - Fuerzas y Cuerpos de Seguridad",
          "archivo": "sargento/conocimientos/tema_22/tema_22_sub22.1_test_02.json",
          "preguntas": 20,
          "subtema": "22.1"
        },
        {
          "nombre": "Test 3 — Tema 22 - Fuerzas y Cuerpos de Seguridad",
          "archivo": "sargento/conocimientos/tema_22/tema_22_sub22.1_test_03.json",
          "preguntas": 20,
          "subtema": "22.1"
        },
        {
          "nombre": "Test 4 — Tema 22 - Fuerzas y Cuerpos de Seguridad",
          "archivo": "sargento/conocimientos/tema_22/tema_22_sub22.1_test_04.json",
          "preguntas": 20,
          "subtema": "22.1"
        },
        {
          "nombre": "Test 5 — Tema 22 - Fuerzas y Cuerpos de Seguridad",
          "archivo": "sargento/conocimientos/tema_22/tema_22_sub22.1_test_05.json",
          "preguntas": 20,
          "subtema": "22.1"
        },
        {
          "nombre": "Test 6 — Tema 22 - Fuerzas y Cuerpos de Seguridad",
          "archivo": "sargento/conocimientos/tema_22/tema_22_sub22.1_test_06.json",
          "preguntas": 20,
          "subtema": "22.1"
        },
        {
          "nombre": "Test 7 — Tema 22 - Fuerzas y Cuerpos de Seguridad",
          "archivo": "sargento/conocimientos/tema_22/tema_22_sub22.1_test_07.json",
          "preguntas": 20,
          "subtema": "22.1"
        },
        {
          "nombre": "Test 8 — Tema 22 - Fuerzas y Cuerpos de Seguridad",
          "archivo": "sargento/conocimientos/tema_22/tema_22_sub22.1_test_08.json",
          "preguntas": 20,
          "subtema": "22.1"
        },
        {
          "nombre": "Test 9 — Tema 22 - Fuerzas y Cuerpos de Seguridad",
          "archivo": "sargento/conocimientos/tema_22/tema_22_sub22.1_test_09.json",
          "preguntas": 20,
          "subtema": "22.1"
        },
        {
          "nombre": "Test 10 — Tema 22 - Fuerzas y Cuerpos de Seguridad",
          "archivo": "sargento/conocimientos/tema_22/tema_22_sub22.1_test_10.json",
          "preguntas": 20,
          "subtema": "22.1"
        },
        {
          "nombre": "Test 11 — Tema 22 - Fuerzas y Cuerpos de Seguridad",
          "archivo": "sargento/conocimientos/tema_22/tema_22_sub22.1_test_11.json",
          "preguntas": 20,
          "subtema": "22.1"
        },
        {
          "nombre": "Test 12 — Tema 22 - Fuerzas y Cuerpos de Seguridad",
          "archivo": "sargento/conocimientos/tema_22/tema_22_sub22.1_test_12.json",
          "preguntas": 20,
          "subtema": "22.1"
        },
        {
          "nombre": "Test 13 — Tema 22 - Fuerzas y Cuerpos de Seguridad",
          "archivo": "sargento/conocimientos/tema_22/tema_22_sub22.1_test_13.json",
          "preguntas": 20,
          "subtema": "22.1"
        },
        {
          "nombre": "Test 14 — Tema 22 - Fuerzas y Cuerpos de Seguridad",
          "archivo": "sargento/conocimientos/tema_22/tema_22_sub22.1_test_14.json",
          "preguntas": 20,
          "subtema": "22.1"
        },
        {
          "nombre": "Test 15 — Tema 22 - Fuerzas y Cuerpos de Seguridad",
          "archivo": "sargento/conocimientos/tema_22/tema_22_sub22.1_test_15.json",
          "preguntas": 20,
          "subtema": "22.1"
        },
        {
          "nombre": "Test 16 — Tema 22 - Fuerzas y Cuerpos de Seguridad",
          "archivo": "sargento/conocimientos/tema_22/tema_22_sub22.1_test_16.json",
          "preguntas": 20,
          "subtema": "22.1"
        },
        {
          "nombre": "Test 17 — Tema 22 - Fuerzas y Cuerpos de Seguridad",
          "archivo": "sargento/conocimientos/tema_22/tema_22_sub22.1_test_17.json",
          "preguntas": 20,
          "subtema": "22.1"
        },
        {
          "nombre": "Test 1 — Tema 22 - Fuerzas y Cuerpos de Seguridad",
          "archivo": "sargento/conocimientos/tema_22/tema_22_sub22.2_test_01.json",
          "preguntas": 20,
          "subtema": "22.2"
        },
        {
          "nombre": "Test 2 — Tema 22 - Fuerzas y Cuerpos de Seguridad",
          "archivo": "sargento/conocimientos/tema_22/tema_22_sub22.2_test_02.json",
          "preguntas": 20,
          "subtema": "22.2"
        },
        {
          "nombre": "Test 3 — Tema 22 - Fuerzas y Cuerpos de Seguridad",
          "archivo": "sargento/conocimientos/tema_22/tema_22_sub22.2_test_03.json",
          "preguntas": 20,
          "subtema": "22.2"
        },
        {
          "nombre": "Test 4 — Tema 22 - Fuerzas y Cuerpos de Seguridad",
          "archivo": "sargento/conocimientos/tema_22/tema_22_sub22.2_test_04.json",
          "preguntas": 20,
          "subtema": "22.2"
        },
        {
          "nombre": "Test 5 — Tema 22 - Fuerzas y Cuerpos de Seguridad",
          "archivo": "sargento/conocimientos/tema_22/tema_22_sub22.2_test_05.json",
          "preguntas": 20,
          "subtema": "22.2"
        },
        {
          "nombre": "Test 6 — Tema 22 - Fuerzas y Cuerpos de Seguridad",
          "archivo": "sargento/conocimientos/tema_22/tema_22_sub22.2_test_06.json",
          "preguntas": 20,
          "subtema": "22.2"
        },
        {
          "nombre": "Test 7 — Tema 22 - Fuerzas y Cuerpos de Seguridad",
          "archivo": "sargento/conocimientos/tema_22/tema_22_sub22.2_test_07.json",
          "preguntas": 20,
          "subtema": "22.2"
        }
      ],
      "total_preguntas": 480
    },
    "tema_23": {
      "tests": [
        {
          "nombre": "Test 1 — Estatuto del Personal",
          "archivo": "sargento/conocimientos/tema_23/tema_23_sub23.1_test_01.json",
          "preguntas": 20,
          "subtema": "23.1"
        },
        {
          "nombre": "Test 2 — Tema 23 - Estatuto del Personal",
          "archivo": "sargento/conocimientos/tema_23/tema_23_sub23.1_test_02.json",
          "preguntas": 20,
          "subtema": "23.1"
        },
        {
          "nombre": "Test 3 — Tema 23 - Estatuto del Personal",
          "archivo": "sargento/conocimientos/tema_23/tema_23_sub23.1_test_03.json",
          "preguntas": 20,
          "subtema": "23.1"
        },
        {
          "nombre": "Test 2 — Tema 23 - Estatuto del Personal",
          "archivo": "sargento/conocimientos/tema_23/tema_23_sub23.2_test_02.json",
          "preguntas": 20,
          "subtema": "23.2"
        },
        {
          "nombre": "Test 3 — Tema 23 - Estatuto del Personal",
          "archivo": "sargento/conocimientos/tema_23/tema_23_sub23.2_test_03.json",
          "preguntas": 20,
          "subtema": "23.2"
        }
      ],
      "total_preguntas": 100
    }
  }
}